{
    "GNN_DATA": {
        "edges": [
            {
                "dst": 4225584,
                "src": 4224448
            },
            {
                "dst": 4224506,
                "src": 4224448
            },
            {
                "dst": 4225607,
                "src": 4225584
            },
            {
                "dst": 4225594,
                "src": 4225584
            },
            {
                "dst": 4225628,
                "src": 4225607
            },
            {
                "dst": 4225632,
                "src": 4225607
            },
            {
                "dst": 4225632,
                "src": 4225628
            },
            {
                "dst": 4225642,
                "src": 4225632
            },
            {
                "dst": 4225655,
                "src": 4225642
            },
            {
                "dst": 4226448,
                "src": 4225642
            },
            {
                "dst": 4226576,
                "src": 4225655
            },
            {
                "dst": 4225666,
                "src": 4225655
            },
            {
                "dst": 4226589,
                "src": 4226576
            },
            {
                "dst": 4225682,
                "src": 4226589
            },
            {
                "dst": 4226560,
                "src": 4225682
            },
            {
                "dst": 4225715,
                "src": 4225682
            },
            {
                "dst": 4224555,
                "src": 4226560
            },
            {
                "dst": "loopSeerDum",
                "src": 4226560
            },
            {
                "dst": 4224611,
                "src": 4224555
            },
            {
                "dst": "loopSeerDum",
                "src": 4224555
            },
            {
                "dst": 4224595,
                "src": 4224555
            },
            {
                "dst": 4224911,
                "src": 4224611
            },
            {
                "dst": "loopSeerDum",
                "src": 4224611
            },
            {
                "dst": 4224929,
                "src": 4224911
            },
            {
                "dst": 4226152,
                "src": 4224911
            },
            {
                "dst": "loopSeerDum",
                "src": 4224911
            },
            {
                "dst": 4224934,
                "src": 4224929
            },
            {
                "dst": "loopSeerDum",
                "src": 4224929
            },
            {
                "dst": 4224951,
                "src": 4224934
            },
            {
                "dst": "loopSeerDum",
                "src": 4224934
            },
            {
                "dst": 4226368,
                "src": 4224951
            },
            {
                "dst": 4224963,
                "src": 4224951
            },
            {
                "dst": "loopSeerDum",
                "src": 4224951
            },
            {
                "dst": 4226414,
                "src": 4226368
            },
            {
                "dst": "loopSeerDum",
                "src": 4226368
            },
            {
                "dst": 4226427,
                "src": 4226414
            },
            {
                "dst": "loopSeerDum",
                "src": 4226414
            },
            {
                "dst": 4226432,
                "src": 4226427
            },
            {
                "dst": "loopSeerDum",
                "src": 4226427
            },
            {
                "dst": "loopSeerDum",
                "src": 4226432
            },
            {
                "dst": 4226155,
                "src": 4226432
            },
            {
                "dst": 4224970,
                "src": 4224963
            },
            {
                "dst": 4224980,
                "src": 4224963
            },
            {
                "dst": "loopSeerDum",
                "src": 4224963
            },
            {
                "dst": 4225456,
                "src": 4224970
            },
            {
                "dst": 4224980,
                "src": 4224970
            },
            {
                "dst": "loopSeerDum",
                "src": 4224970
            },
            {
                "dst": 4225473,
                "src": 4225456
            },
            {
                "dst": 4225462,
                "src": 4225456
            },
            {
                "dst": "loopSeerDum",
                "src": 4225456
            },
            {
                "dst": "loopSeerDum",
                "src": 4225473
            },
            {
                "dst": 4224906,
                "src": 4225473
            },
            {
                "dst": "loopSeerDum",
                "src": 4225462
            },
            {
                "dst": 4225473,
                "src": 4225462
            },
            {
                "dst": 4224980,
                "src": 4225462
            },
            {
                "dst": 4224992,
                "src": 4224980
            },
            {
                "dst": "loopSeerDum",
                "src": 4224980
            },
            {
                "dst": "loopSeerDum",
                "src": 4224992
            },
            {
                "dst": 4225009,
                "src": 4224992
            },
            {
                "dst": "loopSeerDum",
                "src": 4225009
            },
            {
                "dst": 4226064,
                "src": 4225009
            },
            {
                "dst": 4225021,
                "src": 4225009
            },
            {
                "dst": 4225735,
                "src": 4225715
            },
            {
                "dst": 4226660,
                "src": 4225715
            },
            {
                "dst": 4225749,
                "src": 4225735
            },
            {
                "dst": "loopSeerDum",
                "src": 4225735
            },
            {
                "dst": 4226748,
                "src": 4225749
            },
            {
                "dst": 4225760,
                "src": 4225749
            },
            {
                "dst": "loopSeerDum",
                "src": 4225749
            },
            {
                "dst": 4226767,
                "src": 4226748
            },
            {
                "dst": "loopSeerDum",
                "src": 4226748
            },
            {
                "dst": 4225760,
                "src": 4226767
            },
            {
                "dst": "loopSeerDum",
                "src": 4226767
            },
            {
                "dst": 4225768,
                "src": 4225760
            },
            {
                "dst": 4226632,
                "src": 4225760
            },
            {
                "dst": "loopSeerDum",
                "src": 4225760
            },
            {
                "dst": 4225787,
                "src": 4225768
            },
            {
                "dst": 4225772,
                "src": 4225768
            },
            {
                "dst": "loopSeerDum",
                "src": 4225768
            },
            {
                "dst": 4225801,
                "src": 4225787
            },
            {
                "dst": "loopSeerDum",
                "src": 4225787
            },
            {
                "dst": 4225821,
                "src": 4225801
            },
            {
                "dst": "loopSeerDum",
                "src": 4225801
            },
            {
                "dst": 4225840,
                "src": 4225801
            },
            {
                "dst": 4225840,
                "src": 4225821
            },
            {
                "dst": "loopSeerDum",
                "src": 4225821
            },
            {
                "dst": 4225829,
                "src": 4225821
            },
            {
                "dst": "loopSeerDum",
                "src": 4225840
            },
            {
                "dst": 4224555,
                "src": 4225840
            },
            {
                "dst": 4225777,
                "src": 4225772
            },
            {
                "dst": "loopSeerDum",
                "src": 4225772
            },
            {
                "dst": 4225787,
                "src": 4225772
            },
            {
                "dst": 4225782,
                "src": 4225777
            },
            {
                "dst": "loopSeerDum",
                "src": 4225777
            },
            {
                "dst": 4225787,
                "src": 4225782
            },
            {
                "dst": "loopSeerDum",
                "src": 4225782
            },
            {
                "dst": 4226647,
                "src": 4226632
            },
            {
                "dst": "loopSeerDum",
                "src": 4226632
            },
            {
                "dst": 4226655,
                "src": 4226647
            },
            {
                "dst": 4225768,
                "src": 4226647
            },
            {
                "dst": "loopSeerDum",
                "src": 4226647
            },
            {
                "dst": 4224546,
                "src": 4226655
            },
            {
                "dst": "loopSeerDum",
                "src": 4226655
            },
            {
                "dst": 4224555,
                "src": 4224546
            },
            {
                "dst": "loopSeerDum",
                "src": 4224546
            },
            {
                "dst": 4225682,
                "src": 4225666
            },
            {
                "dst": 4225968,
                "src": 4225666
            },
            {
                "dst": "loopSeerDum",
                "src": 4226155
            },
            {
                "dst": 4226166,
                "src": 4226155
            },
            {
                "dst": "loopSeerDum",
                "src": 4226064
            },
            {
                "dst": 4226081,
                "src": 4226064
            },
            {
                "dst": "loopSeerDum",
                "src": 4225021
            },
            {
                "dst": 4225032,
                "src": 4225021
            },
            {
                "dst": 4224696,
                "src": 4225021
            },
            {
                "dst": 4225983,
                "src": 4225968
            },
            {
                "dst": 4225996,
                "src": 4225983
            },
            {
                "dst": 4226011,
                "src": 4225996
            },
            {
                "dst": 4225682,
                "src": 4226011
            },
            {
                "dst": 4226019,
                "src": 4226011
            },
            {
                "dst": "loopSeerDum",
                "src": 4224906
            },
            {
                "dst": 4224911,
                "src": 4224906
            },
            {
                "dst": 4224611,
                "src": 4224595
            },
            {
                "dst": "loopSeerDum",
                "src": 4224595
            },
            {
                "dst": "loopSeerDum",
                "src": 4226152
            },
            {
                "dst": 4226155,
                "src": 4226152
            },
            {
                "dst": "loopSeerDum",
                "src": 4226166
            },
            {
                "dst": 4226203,
                "src": 4226166
            },
            {
                "dst": 4226173,
                "src": 4226166
            },
            {
                "dst": "loopSeerDum",
                "src": 4226081
            },
            {
                "dst": 4226091,
                "src": 4226081
            },
            {
                "dst": "loopSeerDum",
                "src": 4225032
            },
            {
                "dst": 4225064,
                "src": 4225032
            },
            {
                "dst": "loopSeerDum",
                "src": 4224696
            },
            {
                "dst": 4226848,
                "src": 4224696
            },
            {
                "dst": 4224710,
                "src": 4224696
            },
            {
                "dst": "loopSeerDum",
                "src": 4225829
            },
            {
                "dst": 4225607,
                "src": 4225594
            },
            {
                "dst": 4225864,
                "src": 4225594
            },
            {
                "dst": 4226674,
                "src": 4226660
            },
            {
                "dst": 4225735,
                "src": 4226660
            },
            {
                "dst": 4226684,
                "src": 4226674
            },
            {
                "dst": 4226688,
                "src": 4226684
            },
            {
                "dst": 4226814,
                "src": 4226684
            },
            {
                "dst": 4225735,
                "src": 4226688
            },
            {
                "dst": 4226825,
                "src": 4226814
            },
            {
                "dst": 4226560,
                "src": 4226814
            },
            {
                "dst": 4225749,
                "src": 4226825
            },
            {
                "dst": "loopSeerDum",
                "src": 4226825
            },
            {
                "dst": 4225607,
                "src": 4225864
            },
            {
                "dst": 4224514,
                "src": 4224506
            },
            {
                "dst": 4224526,
                "src": 4224514
            },
            {
                "dst": 4225888,
                "src": 4224514
            },
            {
                "dst": 4226536,
                "src": 4224526
            },
            {
                "dst": 4224537,
                "src": 4224526
            },
            {
                "dst": 4224555,
                "src": 4226536
            },
            {
                "dst": 4226320,
                "src": 4226203
            },
            {
                "dst": 4226325,
                "src": 4226320
            },
            {
                "dst": 4226776,
                "src": 4226325
            },
            {
                "dst": 4226336,
                "src": 4226325
            },
            {
                "dst": "loopSeerDum",
                "src": 4226325
            },
            {
                "dst": "loopSeerDum",
                "src": 4226776
            },
            {
                "dst": "loopSeerDum",
                "src": 4226336
            },
            {
                "dst": "loopSeerDum",
                "src": 4226091
            },
            {
                "dst": 4226100,
                "src": 4226091
            },
            {
                "dst": "loopSeerDum",
                "src": 4225064
            },
            {
                "dst": 4226064,
                "src": 4225064
            },
            {
                "dst": 4225072,
                "src": 4225064
            },
            {
                "dst": "loopSeerDum",
                "src": 4226848
            },
            {
                "dst": 4226861,
                "src": 4226848
            },
            {
                "dst": "loopSeerDum",
                "src": 4224710
            },
            {
                "dst": 4224760,
                "src": 4224710
            },
            {
                "dst": 4225376,
                "src": 4224710
            },
            {
                "dst": 4225925,
                "src": 4226100
            },
            {
                "dst": "loopSeerDum",
                "src": 4226100
            },
            {
                "dst": "loopSeerDum",
                "src": 4225925
            },
            {
                "dst": 4225950,
                "src": 4225925
            },
            {
                "dst": 4225568,
                "src": 4225072
            },
            {
                "dst": "loopSeerDum",
                "src": 4225072
            },
            {
                "dst": "loopSeerDum",
                "src": 4225568
            },
            {
                "dst": 4225108,
                "src": 4225568
            },
            {
                "dst": 4226871,
                "src": 4226861
            },
            {
                "dst": "loopSeerDum",
                "src": 4226861
            },
            {
                "dst": "loopSeerDum",
                "src": 4226871
            },
            {
                "dst": 4226880,
                "src": 4226871
            },
            {
                "dst": 4224764,
                "src": 4224760
            },
            {
                "dst": "loopSeerDum",
                "src": 4224760
            },
            {
                "dst": "loopSeerDum",
                "src": 4224764
            },
            {
                "dst": 4224780,
                "src": 4224764
            },
            {
                "dst": "loopSeerDum",
                "src": 4225950
            },
            {
                "dst": "loopSeerDum",
                "src": 4225108
            },
            {
                "dst": "loopSeerDum",
                "src": 4226880
            },
            {
                "dst": "loopSeerDum",
                "src": 4224780
            },
            {
                "dst": 4226189,
                "src": 4226173
            },
            {
                "dst": 4226184,
                "src": 4226173
            },
            {
                "dst": 4226195,
                "src": 4226189
            },
            {
                "dst": "loopSeerDum",
                "src": 4226189
            },
            {
                "dst": "loopSeerDum",
                "src": 4226195
            },
            {
                "dst": 4226189,
                "src": 4226184
            },
            {
                "dst": "loopSeerDum",
                "src": 4226184
            },
            {
                "dst": "loopSeerDum",
                "src": 4225376
            },
            {
                "dst": 4225402,
                "src": 4225376
            },
            {
                "dst": "loopSeerDum",
                "src": 4225402
            },
            {
                "dst": 4224546,
                "src": 4224537
            },
            {
                "dst": 4225897,
                "src": 4225888
            },
            {
                "dst": 4225916,
                "src": 4225897
            },
            {
                "dst": 4226459,
                "src": 4225897
            },
            {
                "dst": 4225925,
                "src": 4225916
            },
            {
                "dst": 4225916,
                "src": 4226448
            },
            {
                "dst": 4226459,
                "src": 4226448
            },
            {
                "dst": 4226475,
                "src": 4226459
            },
            {
                "dst": 4225916,
                "src": 4226475
            },
            {
                "dst": 4226024,
                "src": 4226019
            },
            {
                "dst": 4225925,
                "src": 4226024
            }
        ],
        "nodes": [
            {
                "block_addr": 4224448,
                "constraints": [],
                "instructions": "push|reg|    |push|reg|    |mov|reg|rdi|    |push|reg|    |push|reg|    |push|rbp|    |push|rbx|    |sub|rsp|0x78|    |mov|rbp|qword|ptr|rdi|    |mov|rax|qword|ptr|fs:0x28|    |mov|qword|ptr|rsp|+|0x68|rax|    |xor|eax|eax|    |mov|dword|ptr|rsp|+|0x58|esi|    |mov|rax|qword|ptr|rbp|+|0x18|    |test|rax|rax|    |mov|qword|ptr|rsp|+|0x50|rax|    |je|target_0|    "
            },
            {
                "block_addr": 4225584,
                "constraints": [
                    "<Bool|__eq__|reg|0xfffffffffe000000|>    |<Bool|__eq__|__add__|mem_0|0x18|0x1a|>    |<Bool|__eq__|mem_2|0x0|>    "
                ],
                "instructions": "mov|eax|dword|ptr|rdi|+|0x48|    |mov|edx|eax|    |and|edx|0x10|    |je|target_0|    "
            },
            {
                "block_addr": 4225607,
                "constraints": [
                    "<Bool|__eq__|__and__|mem_0|1|0|>    ",
                    "<Bool|__eq__|__and__|mem_0|16|0|>    "
                ],
                "instructions": "and|eax|0x204|    |mov|rsi|qword|ptr|rbp|+|0x30|    |mov|edi|0xffffff9c|    |cmp|eax|0x200|    |jne|target_0|    "
            },
            {
                "block_addr": 4225628,
                "constraints": [
                    "<Bool|__eq__|__and__|mem_0|0x204|0x200|>    "
                ],
                "instructions": "mov|edi|dword|ptr|reg|+|0x2c|    |lea|rcx|rsp|+|0x64|    |call|0x40a4a0|    "
            },
            {
                "block_addr": 4225632,
                "constraints": [
                    "<Bool|__ne__|__and__|mem_0|0x204|0x200|>    "
                ],
                "instructions": "lea|rcx|rsp|+|0x64|    |call|0x40a4a0|    "
            },
            {
                "block_addr": 4225642,
                "constraints": [],
                "instructions": "test|rax|rax|    |mov|qword|ptr|rbp|+|0x18|rax|    |je|target_0|    "
            },
            {
                "block_addr": 4225655,
                "constraints": [
                    "<Bool|__ne__|ret|0x0|>    "
                ],
                "instructions": "cmp|word|ptr|rbp|+|0x70|0xb|    |je|target_0|    "
            },
            {
                "block_addr": 4226576,
                "constraints": [
                    "<Bool|__eq__|mem_0|0xb|>    "
                ],
                "instructions": "xor|edx|edx|    |mov|rsi|rbp|    |mov|rdi|reg|    |call|0x406a40|    "
            },
            {
                "block_addr": 4226589,
                "constraints": [],
                "instructions": "mov|word|ptr|rbp|+|0x70|ax|    |jmp|target_0|    "
            },
            {
                "block_addr": 4225682,
                "constraints": [
                    "<Bool|__ne__|ret|0|>    ",
                    "<Bool|__eq__|__and__|mem_0|0x100|0x0|>    "
                ],
                "instructions": "cmp|qword|ptr|reg|+|0x40|1|    |sbb|rax|rax|    |and|eax|0x186a1|    |sub|rax|1|    |cmp|dword|ptr|rsp|+|0x58|2|    |mov|qword|ptr|rsp|+|0x38|rax|    |je|target_0|    "
            },
            {
                "block_addr": 4226560,
                "constraints": [
                    "<Bool|__ne__|reg|0x3|>    ",
                    "<Bool|__eq__|reg|0x2|>    "
                ],
                "instructions": "mov|byte|ptr|rsp|+|0x5f|0|    |mov|edi|dword|ptr|reg|+|0x48|    |jmp|target_0|    "
            },
            {
                "block_addr": 4224555,
                "constraints": [],
                "instructions": "mov|rcx|qword|ptr|rbp|+|0x48|    |mov|rdx|qword|ptr|rbp|+|0x38|    |mov|qword|ptr|rsp|+|0x40|0|    |cmp|byte|ptr|rdx|+|rcx|-|1|0x2f|    |lea|rax|rcx|-|1|    |cmovne|rax|rcx|    |and|edi|4|    |mov|qword|ptr|rsp|+|0x48|rax|    |je|target_0|    "
            },
            {
                "block_addr": 4224611,
                "constraints": [
                    "<Bool|__eq__|__add__|If|__eq__|mem_11|47|__add__|0xffffffffffffffff|mem_0|mem_0|mem_10|0xffffffffffffffff|>    ",
                    "<Bool|__eq__|__add__|mem_15|mem_14|0xffffffffffffffff|0xffffffffffffffff|>    |<Bool|__eq__|__and__|mem_0|4|0|>    ",
                    "<Bool|__eq__|__add__|If|__eq__|mem_2|47|__add__|0xffffffffffffffff|mem_0|mem_0|mem_10|0xffffffffffffffff|>    ",
                    "<Bool|__eq__|__add__|If|__eq__|mem_226|47|__add__|0xffffffffffffffff|mem_0|mem_0|mem_10|0xffffffffffffffff|>    ",
                    "<Bool|__eq__|__add__|If|__eq__|mem_484|47|__add__|0xffffffffffffffff|mem_0|mem_0|mem_10|0xffffffffffffffff|>    ",
                    "<Bool|__eq__|__add__|If|__eq__|mem_482|47|__add__|0xffffffffffffffff|mem_0|mem_0|mem_10|0xffffffffffffffff|>    ",
                    "<Bool|__eq__|__add__|If|__eq__|mem_280|47|__add__|0xffffffffffffffff|mem_0|mem_0|mem_10|0xffffffffffffffff|>    ",
                    "<Bool|__eq__|__add__|If|__eq__|mem_90|47|__add__|0xffffffffffffffff|mem_0|mem_0|mem_10|0xffffffffffffffff|>    ",
                    "<Bool|__eq__|__add__|If|__eq__|mem_354|47|__add__|0xffffffffffffffff|mem_0|mem_0|mem_10|0xffffffffffffffff|>    ",
                    "<Bool|__eq__|__add__|mem_15|mem_14|0xffffffffffffffff|0xfffffffffffffffe|>    |<Bool|__eq__|__and__|mem_0|4|0|>    ",
                    "<Bool|__eq__|__add__|If|__eq__|mem_110|47|__add__|0xffffffffffffffff|mem_0|mem_0|mem_10|0xffffffffffffffff|>    ",
                    "<Bool|__eq__|__add__|mem_76|mem_75|0xffffffffffffffff|0xffffffffffffffff|>    |<Bool|__eq__|__and__|mem_0|4|0|>    ",
                    "<Bool|__eq__|__add__|If|__eq__|mem_159|47|__add__|0xffffffffffffffff|mem_51|mem_51|mem_0|0xffffffffffffffff|>    ",
                    "<Bool|__eq__|__add__|If|__eq__|mem_333|47|__add__|0xffffffffffffffff|mem_51|mem_51|mem_0|0xffffffffffffffff|>    ",
                    "<Bool|__eq__|__add__|If|__eq__|mem_331|47|__add__|0xffffffffffffffff|mem_51|mem_51|mem_0|0xffffffffffffffff|>    ",
                    "<Bool|__eq__|__add__|If|__eq__|mem_440|47|__add__|0xffffffffffffffff|mem_51|mem_51|mem_0|0xffffffffffffffff|>    ",
                    "<Bool|__eq__|__add__|If|__eq__|mem_438|47|__add__|0xffffffffffffffff|mem_51|mem_51|mem_0|0xffffffffffffffff|>    ",
                    "<Bool|__eq__|__add__|If|__eq__|mem_199|47|__add__|0xffffffffffffffff|mem_51|mem_51|mem_0|0xffffffffffffffff|>    ",
                    "<Bool|__eq__|__add__|If|__eq__|mem_53|47|__add__|0xffffffffffffffff|mem_51|mem_51|mem_0|0xffffffffffffffff|>    ",
                    "<Bool|__eq__|__add__|If|__eq__|mem_427|47|__add__|0xffffffffffffffff|mem_72|mem_72|mem_0|0xffffffffffffffff|>    ",
                    "<Bool|__eq__|__add__|mem_97|mem_96|0xffffffffffffffff|0xffffffffffffffff|>    |<Bool|__eq__|__and__|mem_0|4|0|>    ",
                    "<Bool|__eq__|__add__|If|__eq__|mem_425|47|__add__|0xffffffffffffffff|mem_72|mem_72|mem_0|0xffffffffffffffff|>    ",
                    "<Bool|__eq__|__add__|If|__eq__|mem_248|47|__add__|0xffffffffffffffff|mem_72|mem_72|mem_0|0xffffffffffffffff|>    ",
                    "<Bool|__eq__|__add__|If|__eq__|mem_74|47|__add__|0xffffffffffffffff|mem_72|mem_72|mem_0|0xffffffffffffffff|>    ",
                    "<Bool|__eq__|__add__|If|__eq__|mem_114|47|__add__|0xffffffffffffffff|mem_25|mem_25|mem_0|0xffffffffffffffff|>    ",
                    "<Bool|__eq__|__add__|mem_50|mem_49|0xffffffffffffffff|0xffffffffffffffff|>    |<Bool|__eq__|__and__|mem_0|4|0|>    ",
                    "<Bool|__eq__|__add__|If|__eq__|mem_402|47|__add__|0xffffffffffffffff|mem_25|mem_25|mem_0|0xffffffffffffffff|>    ",
                    "<Bool|__eq__|__add__|If|__eq__|mem_399|47|__add__|0xffffffffffffffff|mem_25|mem_25|mem_0|0xffffffffffffffff|>    ",
                    "<Bool|__eq__|__add__|If|__eq__|mem_238|47|__add__|0xffffffffffffffff|mem_25|mem_25|mem_0|0xffffffffffffffff|>    ",
                    "<Bool|__eq__|__add__|If|__eq__|mem_236|47|__add__|0xffffffffffffffff|mem_25|mem_25|mem_0|0xffffffffffffffff|>    ",
                    "<Bool|__eq__|__add__|If|__eq__|mem_27|47|__add__|0xffffffffffffffff|mem_25|mem_25|mem_0|0xffffffffffffffff|>    ",
                    "<Bool|__eq__|__add__|mem_70|mem_69|0xffffffffffffffff|0xffffffffffffffff|>    |<Bool|__eq__|__and__|mem_0|4|0|>    ",
                    "<Bool|__eq__|__add__|If|__eq__|mem_295|47|__add__|0xffffffffffffffff|mem_45|mem_45|mem_0|0xffffffffffffffff|>    ",
                    "<Bool|__eq__|__add__|If|__eq__|mem_293|47|__add__|0xffffffffffffffff|mem_45|mem_45|mem_0|0xffffffffffffffff|>    ",
                    "<Bool|__eq__|__add__|If|__eq__|mem_47|47|__add__|0xffffffffffffffff|mem_45|mem_45|mem_0|0xffffffffffffffff|>    ",
                    "<Bool|__eq__|__add__|mem_66|mem_65|0xffffffffffffffff|0xffffffffffffffff|>    |<Bool|__eq__|__and__|mem_0|4|0|>    ",
                    "<Bool|__eq__|__add__|mem_88|mem_87|0xffffffffffffffff|0xffffffffffffffff|>    |<Bool|__eq__|__and__|mem_0|4|0|>    "
                ],
                "instructions": "mov|rax|qword|ptr|rsp|+|0x48|    |mov|rbx|qword|ptr|reg|+|0x30|    |mov|byte|ptr|rsp|+|0x5e|0|    |mov|byte|ptr|rsp|+|0x5d|0|    |mov|qword|ptr|rsp|+|8|0|    |mov|qword|ptr|rsp|+|0x10|0|    |add|rax|1|    |mov|qword|ptr|rsp|+|0x20|rbp|    |sub|rbx|rax|    |mov|qword|ptr|rsp|+|0x18|rax|    |mov|rax|qword|ptr|rbp|+|0x58|    |mov|qword|ptr|rsp|+|0x28|rbx|    |xor|ebx|ebx|    |add|rax|1|    |mov|qword|ptr|rsp|+|0x30|rax|    |jmp|target_0|    "
            },
            {
                "block_addr": 4224911,
                "constraints": [],
                "instructions": "mov|rax|qword|ptr|rsp|+|0x20|    |mov|reg|qword|ptr|rax|+|0x18|    |test|reg|reg|    |je|target_0|    "
            },
            {
                "block_addr": 4224929,
                "constraints": [],
                "instructions": "call|0x4019a0|    "
            },
            {
                "block_addr": 4224934,
                "constraints": [],
                "instructions": "mov|rdi|reg|    |mov|dword|ptr|rax|0|    |mov|reg|rax|    |call|0x401c10|    "
            },
            {
                "block_addr": 4224951,
                "constraints": [
                    "<Bool|__eq__|ret|0xffffffffffffffff|>    "
                ],
                "instructions": "test|rax|rax|    |mov|rbp|rax|    |je|target_0|    "
            },
            {
                "block_addr": 4226368,
                "constraints": [
                    "<Bool|__eq__|ret|0x0|>    "
                ],
                "instructions": "mov|eax|dword|ptr|reg|    |mov|rbp|qword|ptr|rsp|+|0x20|    |test|eax|eax|    |je|target_0|    "
            },
            {
                "block_addr": 4226414,
                "constraints": [],
                "instructions": "mov|rdi|qword|ptr|rbp|+|0x18|    |test|rdi|rdi|    |je|target_0|    "
            },
            {
                "block_addr": 4226427,
                "constraints": [],
                "instructions": "call|0x401b60|    "
            },
            {
                "block_addr": 4226432,
                "constraints": [],
                "instructions": "mov|qword|ptr|rbp|+|0x18|0|    |jmp|target_0|    "
            },
            {
                "block_addr": "loopSeerDum",
                "constraints": [
                    "<Bool|__eq__|__add__|ret|0x30|0xffffffffffffffd7|>    ",
                    "<Bool|__eq__|__add__|mem_0|0x70|0x72|>    ",
                    "<Bool|__eq__|__add__|ret|0x58|0xffffffffffffffff|>    |<Bool|__eq__|__add__|ret|0x48|0xffffffffffffffef|>    |<Bool|__eq__|__add__|ret|0x8|0xffffffffffffffaf|>    |<Bool|__eq__|__add__|ret|0x80|0x27|>    ",
                    "<Bool|__ne__|ret|0|>    ",
                    "<Bool|__eq__|ret|0|>    ",
                    "<Bool|__gt__|__add__|0xffffffffffffffff|mem_9|__mul__|0xffffffffffffffff|If|__eq__|mem_11|47|__add__|0xffffffffffffffff|mem_0|mem_0|ret|>    ",
                    "<Bool|__le__|__add__|0xffffffffffffffff|mem_9|__mul__|0xffffffffffffffff|If|__eq__|mem_11|47|__add__|0xffffffffffffffff|mem_0|mem_0|ret|>    ",
                    "<Bool|__eq__|ret|0xffffffffffffffff|>    ",
                    "<Bool|__ge__|__add__|ret|0x1|If|__eq__|mem_11|47|__add__|0xffffffffffffffff|mem_0|mem_0|ret|>    ",
                    "<Bool|__lt__|__add__|ret|0x1|If|__eq__|mem_11|47|__add__|0xffffffffffffffff|mem_0|mem_0|ret|>    ",
                    "<Bool|__ne__|ret|0x0|>    ",
                    "<Bool|__eq__|ret|0x0|>    ",
                    "<Bool|__ne__|reg|0x3|>    ",
                    "<Bool|__eq__|reg|0x3|>    ",
                    "<Bool|__ge__|__add__|ret|0x1|If|__eq__|mem_2|47|__add__|0xffffffffffffffff|mem_0|mem_0|ret|>    ",
                    "<Bool|__lt__|__add__|ret|0x1|If|__eq__|mem_2|47|__add__|0xffffffffffffffff|mem_0|mem_0|ret|>    ",
                    "<Bool|__ne__|__and__|mem_0|24|24|>    ",
                    "<Bool|__eq__|__and__|mem_0|24|24|>    ",
                    "<Bool|__ne__|mem_0|0x7|>    ",
                    "<Bool|__eq__|mem_0|0x7|>    ",
                    "<Bool|__ne__|Concat|0|If|__eq__|reg|0x3|1|0|0|>    ",
                    "<Bool|__eq__|Concat|0|If|__eq__|reg|0x3|1|0|0|>    ",
                    "<Bool|__eq__|__and__|mem_0|0x200|0x0|>    ",
                    "<Bool|__eq__|LShR|ZeroExt|32|ret|0x1f|0|>    ",
                    "<Bool|__ne__|LShR|ZeroExt|32|ret|0x1f|0|>    ",
                    "<Bool|__eq__|__add__|mem_15|mem_14|0xffffffffffffffff|0xffffffffffffffff|>    |<Bool|__ne__|__and__|mem_0|4|0|>    ",
                    "<Bool|__eq__|__add__|mem_15|mem_14|0xffffffffffffffff|0xffffffffffffffff|>    |<Bool|__eq__|__and__|mem_0|4|0|>    ",
                    "<Bool|__ne__|__and__|mem_0|2|0|>    ",
                    "<Bool|__eq__|__and__|mem_0|2|0|>    ",
                    "<Bool|__ne__|__and__|mem_0|0x200|0x0|>    ",
                    "<Bool|__eq__|ret|0xffffffc000000000|>    |<Bool|__eq__|__add__|mem_0|0x40|0x42|>    ",
                    "<Bool|__eq__|ret|0xfffffffffffffff0|>    |<Bool|__eq__|__add__|mem_0|0x40|0x42|>    ",
                    "<Bool|__eq__|__add__|If|__eq__|mem_637|47|__add__|0xffffffffffffffff|mem_0|mem_0|mem_10|0xffffffffffffffff|>    ",
                    "<Bool|__eq__|__add__|If|__eq__|mem_635|47|__add__|0xffffffffffffffff|mem_0|mem_0|mem_10|0xffffffffffffffff|>    ",
                    "<Bool|__ne__|mem_0|0|>    ",
                    "<Bool|__eq__|mem_0|0|>    ",
                    "<Bool|__ne__|Concat|mem_180|mem_0|0x2e|>    ",
                    "<Bool|__eq__|Concat|mem_180|mem_0|0x2e|>    ",
                    "<Bool|__eq__|ret|0xffffff0000000000|>    |<Bool|__eq__|__add__|mem_0|0x40|0x42|>    ",
                    "<Bool|__eq__|ret|0xfffffff000000000|>    |<Bool|__eq__|__add__|mem_0|0x40|0x42|>    ",
                    "<Bool|__eq__|__add__|If|__eq__|mem_624|47|__add__|0xffffffffffffffff|mem_0|mem_0|mem_10|0xffffffffffffffff|>    ",
                    "<Bool|__eq__|__add__|If|__eq__|mem_622|47|__add__|0xffffffffffffffff|mem_0|mem_0|mem_10|0xffffffffffffffff|>    ",
                    "<Bool|__eq__|__add__|ret|0x13|0x14|>    |<Bool|__ne__|mem_0|46|>    ",
                    "<Bool|__eq__|__add__|ret|0x13|0x14|>    |<Bool|__eq__|mem_0|46|>    ",
                    "<Bool|__eq__|ret|0xfffffffff0000000|>    |<Bool|__eq__|__add__|mem_0|0x40|0x42|>    ",
                    "<Bool|__eq__|__add__|ret|0x13|0xfffffffff0000013|>    |<Bool|__ne__|mem_0|46|>    ",
                    "<Bool|__eq__|__add__|ret|0x13|0xfffffffff0000013|>    |<Bool|__eq__|mem_0|46|>    ",
                    "<Bool|__eq__|ret|0xffffffff00000000|>    |<Bool|__eq__|__add__|mem_0|0x40|0x42|>    ",
                    "<Bool|__eq__|__add__|If|__eq__|mem_590|47|__add__|0xffffffffffffffff|mem_51|mem_51|mem_0|0xffffffffffffffff|>    ",
                    "<Bool|__eq__|LShR|ZeroExt|32|mem_0|0x1f|0|>    ",
                    "<Bool|__ne__|LShR|ZeroExt|32|mem_0|0x1f|0|>    ",
                    "<Bool|__ne__|__and__|mem_0|32|0|>    ",
                    "<Bool|__eq__|__and__|mem_0|32|0|>    ",
                    "<Bool|__eq__|ret|0xffffff8000000000|>    |<Bool|__eq__|__add__|mem_0|0x40|0x42|>    ",
                    "<Bool|__eq__|__add__|If|__eq__|mem_587|47|__add__|0xffffffffffffffff|mem_51|mem_51|mem_0|0xffffffffffffffff|>    ",
                    "<Bool|__eq__|__add__|mem_76|mem_75|0xffffffffffffffff|0xffffffffffffffff|>    |<Bool|__ne__|__and__|mem_0|4|0|>    ",
                    "<Bool|__eq__|__add__|If|__eq__|mem_584|47|__add__|0xffffffffffffffff|mem_51|mem_51|mem_0|0xffffffffffffffff|>    ",
                    "<Bool|__eq__|__add__|mem_76|mem_75|0xffffffffffffffff|0xffffffffffffffff|>    |<Bool|__eq__|__and__|mem_0|4|0|>    ",
                    "<Bool|__eq__|ret|0xfffe000000000000|>    |<Bool|__eq__|__add__|mem_0|0x40|0x42|>    ",
                    "<Bool|__ne__|Concat|mem_175|mem_0|0x2e|>    ",
                    "<Bool|__eq__|Concat|mem_175|mem_0|0x2e|>    ",
                    "<Bool|__gt__|__add__|0xffffffffffffffff|mem_0|__mul__|0xffffffffffffffff|If|__eq__|mem_54|47|__add__|0xffffffffffffffff|mem_52|mem_52|ret|>    ",
                    "<Bool|__le__|__add__|0xffffffffffffffff|mem_0|__mul__|0xffffffffffffffff|If|__eq__|mem_54|47|__add__|0xffffffffffffffff|mem_52|mem_52|ret|>    ",
                    "<Bool|__eq__|__add__|mem_97|mem_96|0xffffffffffffffff|0xffffffffffffffff|>    |<Bool|__ne__|__and__|mem_0|4|0|>    ",
                    "<Bool|__eq__|__add__|mem_97|mem_96|0xffffffffffffffff|0xffffffffffffffff|>    |<Bool|__eq__|__and__|mem_0|4|0|>    ",
                    "<Bool|__eq__|ret|0xffffffffffff8000|>    |<Bool|__eq__|__add__|mem_0|0x40|0x42|>    ",
                    "<Bool|__eq__|__add__|If|__eq__|mem_563|47|__add__|0xffffffffffffffff|mem_72|mem_72|mem_0|0xffffffffffffffff|>    ",
                    "<Bool|__eq__|__add__|If|__eq__|mem_561|47|__add__|0xffffffffffffffff|mem_72|mem_72|mem_0|0xffffffffffffffff|>    ",
                    "<Bool|__ne__|Concat|mem_171|mem_0|0x2e|>    ",
                    "<Bool|__eq__|Concat|mem_171|mem_0|0x2e|>    ",
                    "<Bool|__eq__|ret|0xffffffffe0000000|>    |<Bool|__eq__|__add__|mem_0|0x40|0x42|>    ",
                    "<Bool|__ne__|Concat|mem_168|mem_0|0x2e|>    ",
                    "<Bool|__eq__|Concat|mem_168|mem_0|0x2e|>    ",
                    "<Bool|__eq__|ret|0x1|>    |<Bool|__eq__|__add__|mem_0|0x40|0x42|>    ",
                    "<Bool|__eq__|__add__|mem_50|mem_49|0xffffffffffffffff|0xffffffffffffffff|>    |<Bool|__ne__|__and__|mem_0|4|0|>    ",
                    "<Bool|__eq__|__add__|mem_50|mem_49|0xffffffffffffffff|0xffffffffffffffff|>    |<Bool|__eq__|__and__|mem_0|4|0|>    ",
                    "<Bool|__eq__|__add__|ret|0x13|0x3|>    |<Bool|__ne__|mem_0|46|>    ",
                    "<Bool|__eq__|__add__|ret|0x13|0x3|>    |<Bool|__eq__|mem_0|46|>    ",
                    "<Bool|__eq__|__add__|If|__eq__|mem_535|47|__add__|0xffffffffffffffff|mem_25|mem_25|mem_0|0xffffffffffffffff|>    ",
                    "<Bool|__eq__|__add__|If|__eq__|mem_533|47|__add__|0xffffffffffffffff|mem_25|mem_25|mem_0|0xffffffffffffffff|>    ",
                    "<Bool|__gt__|__add__|0xffffffffffffffff|mem_0|__mul__|0xffffffffffffffff|If|__eq__|mem_28|47|__add__|0xffffffffffffffff|mem_26|mem_26|ret|>    ",
                    "<Bool|__le__|__add__|0xffffffffffffffff|mem_0|__mul__|0xffffffffffffffff|If|__eq__|mem_28|47|__add__|0xffffffffffffffff|mem_26|mem_26|ret|>    ",
                    "<Bool|__eq__|__add__|If|__eq__|mem_527|47|__add__|0xffffffffffffffff|mem_45|mem_45|mem_0|0xffffffffffffffff|>    ",
                    "<Bool|__eq__|__add__|mem_70|mem_69|0xffffffffffffffff|0xffffffffffffffff|>    |<Bool|__ne__|__and__|mem_0|4|0|>    ",
                    "<Bool|__eq__|__add__|If|__eq__|mem_524|47|__add__|0xffffffffffffffff|mem_45|mem_45|mem_0|0xffffffffffffffff|>    ",
                    "<Bool|__eq__|__add__|mem_70|mem_69|0xffffffffffffffff|0xfffffffffffffffe|>    |<Bool|__ne__|__and__|mem_0|4|0|>    ",
                    "<Bool|__eq__|__add__|mem_70|mem_69|0xffffffffffffffff|0xfffffffffffffffe|>    |<Bool|__eq__|__and__|mem_0|4|0|>    ",
                    "<Bool|__ne__|Concat|mem_161|mem_0|0x2e|>    ",
                    "<Bool|__eq__|Concat|mem_161|mem_0|0x2e|>    ",
                    "<Bool|__gt__|__add__|0xffffffffffffffff|mem_0|__mul__|0xffffffffffffffff|If|__eq__|mem_48|47|__add__|0xffffffffffffffff|mem_46|mem_46|ret|>    ",
                    "<Bool|__le__|__add__|0xffffffffffffffff|mem_0|__mul__|0xffffffffffffffff|If|__eq__|mem_48|47|__add__|0xffffffffffffffff|mem_46|mem_46|ret|>    ",
                    "<Bool|__eq__|__add__|mem_66|mem_65|0xffffffffffffffff|0xffffffffffffffff|>    |<Bool|__eq__|__and__|mem_0|4|0|>    ",
                    "<Bool|__gt__|__add__|0xffffffffffffffff|mem_0|__mul__|0xffffffffffffffff|If|__eq__|mem_44|47|__add__|0xffffffffffffffff|mem_42|mem_42|ret|>    ",
                    "<Bool|__le__|__add__|0xffffffffffffffff|mem_0|__mul__|0xffffffffffffffff|If|__eq__|mem_44|47|__add__|0xffffffffffffffff|mem_42|mem_42|ret|>    ",
                    "<Bool|__eq__|__add__|mem_88|mem_87|0xffffffffffffffff|0xffffffffffffffff|>    |<Bool|__eq__|__and__|mem_0|4|0|>    ",
                    "<Bool|__ne__|Concat|mem_163|mem_0|0x2e|>    ",
                    "<Bool|__eq__|Concat|mem_163|mem_0|0x2e|>    "
                ],
                "instructions": "no_instructions"
            },
            {
                "block_addr": 4224963,
                "constraints": [
                    "<Bool|__ne__|ret|0x0|>    "
                ],
                "instructions": "test|byte|ptr|reg|+|0x48|0x20|    |jne|target_0|    "
            },
            {
                "block_addr": 4224970,
                "constraints": [
                    "<Bool|__eq__|__and__|mem_0|32|0|>    "
                ],
                "instructions": "cmp|byte|ptr|rax|+|0x13|0x2e|    |je|target_0|    "
            },
            {
                "block_addr": 4225456,
                "constraints": [
                    "<Bool|__eq__|__add__|ret|0x13|0xfffffffff3717fe3|>    |<Bool|__eq__|mem_0|46|>    ",
                    "<Bool|__eq__|__add__|ret|0x13|0x14|>    |<Bool|__eq__|mem_0|46|>    ",
                    "<Bool|__eq__|__add__|ret|0x13|0xfffffffff27c8003|>    |<Bool|__eq__|mem_0|46|>    ",
                    "<Bool|__eq__|__add__|ret|0x13|0xffffffffffffff93|>    |<Bool|__eq__|mem_0|46|>    ",
                    "<Bool|__eq__|__add__|ret|0x13|0xfffffffffff00019|>    |<Bool|__eq__|mem_0|46|>    ",
                    "<Bool|__eq__|__add__|ret|0x13|0xffffffffffff0003|>    |<Bool|__eq__|mem_0|46|>    ",
                    "<Bool|__eq__|__add__|ret|0x13|0xfffffffffffffe1d|>    |<Bool|__eq__|mem_0|46|>    ",
                    "<Bool|__eq__|__add__|ret|0x13|0xfffffffffe000013|>    |<Bool|__eq__|mem_0|46|>    ",
                    "<Bool|__eq__|__add__|ret|0x13|0xfffffffffffffffc|>    |<Bool|__eq__|mem_0|46|>    ",
                    "<Bool|__eq__|__add__|ret|0x13|0xfffffffffffc0023|>    |<Bool|__eq__|mem_0|46|>    ",
                    "<Bool|__eq__|__add__|ret|0x13|0xc000000000000010|>    |<Bool|__eq__|mem_0|46|>    ",
                    "<Bool|__eq__|__add__|ret|0x13|0xfffffffffffffe70|>    |<Bool|__eq__|mem_0|46|>    ",
                    "<Bool|__eq__|__add__|ret|0x13|0xffffff8000000013|>    |<Bool|__eq__|mem_0|46|>    ",
                    "<Bool|__eq__|__add__|ret|0x13|0xfffffffffff40010|>    |<Bool|__eq__|mem_0|46|>    ",
                    "<Bool|__eq__|__add__|ret|0x13|0xfffffffffffff013|>    |<Bool|__eq__|mem_0|46|>    ",
                    "<Bool|__eq__|__add__|ret|0x13|0xf|>    |<Bool|__eq__|mem_0|46|>    ",
                    "<Bool|__eq__|__add__|ret|0x13|0xffffffffffffffe3|>    |<Bool|__eq__|mem_0|46|>    "
                ],
                "instructions": "cmp|byte|ptr|rax|+|0x14|0|    |je|target_0|    "
            },
            {
                "block_addr": 4225473,
                "constraints": [
                    "<Bool|__eq__|Concat|mem_60|mem_0|0x2e|>    ",
                    "<Bool|__eq__|mem_0|0|>    ",
                    "<Bool|__eq__|Concat|mem_46|mem_0|0x2e|>    ",
                    "<Bool|__eq__|Concat|mem_48|mem_0|0x2e|>    ",
                    "<Bool|__eq__|Concat|mem_38|mem_0|0x2e|>    ",
                    "<Bool|__eq__|Concat|mem_138|mem_0|0x2e|>    ",
                    "<Bool|__eq__|Concat|mem_135|mem_0|0x2e|>    ",
                    "<Bool|__eq__|Concat|mem_94|mem_0|0x2e|>    ",
                    "<Bool|__eq__|Concat|mem_133|mem_0|0x2e|>    "
                ],
                "instructions": "mov|reg|qword|ptr|rsp|+|8|    |jmp|target_0|    "
            },
            {
                "block_addr": 4225462,
                "constraints": [
                    "<Bool|__ne__|mem_0|0|>    "
                ],
                "instructions": "cmp|word|ptr|rax|+|0x14|0x2e|    |jne|target_0|    "
            },
            {
                "block_addr": 4224980,
                "constraints": [
                    "<Bool|__ne__|__and__|mem_0|32|0|>    ",
                    "<Bool|__eq__|__add__|ret|0x13|0xfffffffff3717fe3|>    |<Bool|__ne__|mem_0|46|>    ",
                    "<Bool|__ne__|Concat|mem_60|mem_0|0x2e|>    ",
                    "<Bool|__eq__|__add__|ret|0x13|0x14|>    |<Bool|__ne__|mem_0|46|>    ",
                    "<Bool|__ne__|Concat|mem_46|mem_0|0x2e|>    ",
                    "<Bool|__eq__|__add__|ret|0x13|0xfffffffff27c8003|>    |<Bool|__ne__|mem_0|46|>    ",
                    "<Bool|__ne__|Concat|mem_48|mem_0|0x2e|>    ",
                    "<Bool|__eq__|__add__|ret|0x13|0xffffffffffffff93|>    |<Bool|__ne__|mem_0|46|>    ",
                    "<Bool|__ne__|Concat|mem_38|mem_0|0x2e|>    ",
                    "<Bool|__eq__|__add__|ret|0x13|0xfffffffffff00019|>    |<Bool|__ne__|mem_0|46|>    ",
                    "<Bool|__eq__|__add__|ret|0x13|0xffffffffffff0003|>    |<Bool|__ne__|mem_0|46|>    ",
                    "<Bool|__eq__|__add__|ret|0x13|0xfffffffffffffe1d|>    |<Bool|__ne__|mem_0|46|>    ",
                    "<Bool|__eq__|__add__|ret|0x13|0xfffffffffe000013|>    |<Bool|__ne__|mem_0|46|>    ",
                    "<Bool|__eq__|__add__|ret|0x13|0xfffffffffffffffc|>    |<Bool|__ne__|mem_0|46|>    ",
                    "<Bool|__eq__|__add__|ret|0x13|0xfffffffffffc0023|>    |<Bool|__ne__|mem_0|46|>    ",
                    "<Bool|__ne__|Concat|mem_138|mem_0|0x2e|>    ",
                    "<Bool|__eq__|__add__|ret|0x13|0xc000000000000010|>    |<Bool|__ne__|mem_0|46|>    ",
                    "<Bool|__eq__|__add__|ret|0x13|0xfffffffffffffe70|>    |<Bool|__ne__|mem_0|46|>    ",
                    "<Bool|__eq__|__add__|ret|0x13|0xffffff8000000013|>    |<Bool|__ne__|mem_0|46|>    ",
                    "<Bool|__eq__|__add__|ret|0x13|0xfffffffffff40010|>    |<Bool|__ne__|mem_0|46|>    ",
                    "<Bool|__ne__|Concat|mem_135|mem_0|0x2e|>    ",
                    "<Bool|__eq__|__add__|ret|0x13|0xfffffffffffff013|>    |<Bool|__ne__|mem_0|46|>    ",
                    "<Bool|__ne__|Concat|mem_94|mem_0|0x2e|>    ",
                    "<Bool|__eq__|__add__|ret|0x13|0xf|>    |<Bool|__ne__|mem_0|46|>    ",
                    "<Bool|__ne__|Concat|mem_133|mem_0|0x2e|>    ",
                    "<Bool|__eq__|__add__|ret|0x13|0x0|>    ",
                    "<Bool|__eq__|__add__|ret|0x13|0xffffffffffffffe3|>    |<Bool|__ne__|mem_0|46|>    "
                ],
                "instructions": "lea|reg|rbp|+|0x13|    |mov|rdi|reg|    |call|0x401a80|    "
            },
            {
                "block_addr": 4224992,
                "constraints": [],
                "instructions": "mov|rsi|reg|    |mov|rdx|rax|    |mov|rdi|reg|    |mov|reg|rax|    |call|0x406d20|    "
            },
            {
                "block_addr": 4225009,
                "constraints": [],
                "instructions": "test|rax|rax|    |mov|reg|rax|    |je|target_0|    "
            },
            {
                "block_addr": 4225715,
                "constraints": [
                    "<Bool|__ne__|reg|0x2|>    "
                ],
                "instructions": "mov|edx|dword|ptr|reg|+|0x48|    |mov|eax|dword|ptr|rsp|+|0x64|    |and|edx|0x38|    |cmp|edx|0x18|    |je|target_0|    "
            },
            {
                "block_addr": 4225735,
                "constraints": [
                    "<Bool|__ne__|__and__|mem_0|56|24|>    ",
                    "<Bool|__ne__|mem_0|0x2|>    "
                ],
                "instructions": "cmp|dword|ptr|rsp|+|0x58|3|    |mov|regd|1|    |sete|bl|    |test|byte|ptr|reg|+|0x49|2|    |jne|target_0|    "
            },
            {
                "block_addr": 4225749,
                "constraints": [],
                "instructions": "test|byte|ptr|reg|+|0x49|2|    |jne|target_0|    "
            },
            {
                "block_addr": 4226748,
                "constraints": [
                    "<Bool|__ne__|__and__|mem_0|2|0|>    "
                ],
                "instructions": "mov|edi|eax|    |mov|edx|3|    |mov|esi|0x406|    |xor|eax|eax|    |call|0x40a5e0|    "
            },
            {
                "block_addr": 4226767,
                "constraints": [],
                "instructions": "mov|dword|ptr|rsp|+|0x64|eax|    |jmp|target_0|    "
            },
            {
                "block_addr": 4225760,
                "constraints": [
                    "<Bool|__eq__|__and__|mem_0|2|0|>    "
                ],
                "instructions": "test|eax|eax|    |jns|target_0|    "
            },
            {
                "block_addr": 4225768,
                "constraints": [
                    "<Bool|__ne__|LShR|ZeroExt|32|ret|0x1f|0|>    ",
                    "<Bool|__ne__|ret|0x0|>    ",
                    "<Bool|__ne__|LShR|ZeroExt|32|mem_0|0x1f|0|>    "
                ],
                "instructions": "test|bl|bl|    |je|target_0|    "
            },
            {
                "block_addr": 4225787,
                "constraints": [
                    "<Bool|__eq__|Concat|0|If|__eq__|reg|0x3|1|0|0|>    ",
                    "<Bool|__eq__|ret|0xfffffffffffe0000|>    |<Bool|__eq__|__add__|mem_0|0x40|0x42|>    ",
                    "<Bool|__eq__|ret|0xe000000000000000|>    |<Bool|__eq__|__add__|mem_0|0x40|0x42|>    ",
                    "<Bool|__eq__|ret|0xfffffffffffc0000|>    |<Bool|__eq__|__add__|mem_0|0x40|0x42|>    ",
                    "<Bool|__eq__|ret|0x2|>    |<Bool|__eq__|__add__|mem_0|0x40|0x42|>    ",
                    "<Bool|__eq__|ret|0xffffffffffff8000|>    |<Bool|__eq__|__add__|mem_0|0x40|0x42|>    ",
                    "<Bool|__eq__|ret|0xffffffffe0000000|>    |<Bool|__eq__|__add__|mem_0|0x40|0x42|>    ",
                    "<Bool|__eq__|ret|0xfffffffffffffffc|>    |<Bool|__eq__|__add__|mem_0|0x40|0x42|>    ",
                    "<Bool|__eq__|ret|0xfffffe0000000000|>    |<Bool|__eq__|__add__|mem_0|0x40|0x42|>    ",
                    "<Bool|__eq__|ret|0xffffffc000000000|>    |<Bool|__eq__|__add__|mem_0|0x40|0x42|>    ",
                    "<Bool|__eq__|ret|0xfffffffffffff000|>    |<Bool|__eq__|__add__|mem_0|0x40|0x42|>    ",
                    "<Bool|__eq__|ret|0xfffffffe00000000|>    |<Bool|__eq__|__add__|mem_0|0x40|0x42|>    ",
                    "<Bool|__eq__|ret|0xfffffffffc000000|>    |<Bool|__eq__|__add__|mem_0|0x40|0x42|>    ",
                    "<Bool|__eq__|ret|0xfffffffffe000000|>    |<Bool|__eq__|__add__|mem_0|0x40|0x42|>    ",
                    "<Bool|__eq__|ret|0xffffffffffffffc0|>    |<Bool|__eq__|__add__|mem_0|0x40|0x42|>    ",
                    "<Bool|__eq__|ret|0xfffffffffffffe00|>    |<Bool|__eq__|__add__|mem_0|0x40|0x42|>    ",
                    "<Bool|__eq__|ret|0xffffff0000000000|>    |<Bool|__eq__|__add__|mem_0|0x40|0x42|>    ",
                    "<Bool|__eq__|ret|0xfffffffff8000000|>    |<Bool|__eq__|__add__|mem_0|0x40|0x42|>    ",
                    "<Bool|__eq__|ret|0xfffffffffffff800|>    |<Bool|__eq__|__add__|mem_0|0x40|0x42|>    ",
                    "<Bool|__eq__|ret|0xffffffffff000000|>    |<Bool|__eq__|__add__|mem_0|0x40|0x42|>    ",
                    "<Bool|__eq__|ret|0xffffffffffffff00|>    |<Bool|__eq__|__add__|mem_0|0x40|0x42|>    ",
                    "<Bool|__eq__|ret|0xffffffffffff0000|>    |<Bool|__eq__|__add__|mem_0|0x40|0x42|>    ",
                    "<Bool|__eq__|ret|0xfffffffffff00000|>    |<Bool|__eq__|__add__|mem_0|0x40|0x42|>    ",
                    "<Bool|__eq__|ret|0xf800000000000000|>    |<Bool|__eq__|__add__|mem_0|0x40|0x42|>    "
                ],
                "instructions": "or|word|ptr|rbp|+|0x72|1|    |mov|rdi|qword|ptr|rbp|+|0x18|    |call|0x401b60|    "
            },
            {
                "block_addr": 4225801,
                "constraints": [],
                "instructions": "mov|edi|dword|ptr|reg|+|0x48|    |mov|qword|ptr|rbp|+|0x18|0|    |test|edi|0x200|    |je|target_0|    "
            },
            {
                "block_addr": 4225821,
                "constraints": [
                    "<Bool|__ne__|__and__|mem_0|0x200|0x0|>    "
                ],
                "instructions": "mov|eax|dword|ptr|rsp|+|0x64|    |test|eax|eax|    |js|target_0|    "
            },
            {
                "block_addr": 4225840,
                "constraints": [
                    "<Bool|__eq__|__and__|mem_0|0x200|0x0|>    "
                ],
                "instructions": "mov|qword|ptr|rbp|+|0x18|0|    |mov|byte|ptr|rsp|+|0x5f|0|    |jmp|target_0|    "
            },
            {
                "block_addr": 4225772,
                "constraints": [
                    "<Bool|__ne__|Concat|0|If|__eq__|reg|0x3|1|0|0|>    "
                ],
                "instructions": "test|regb|regb|    |je|target_0|    "
            },
            {
                "block_addr": 4225777,
                "constraints": [],
                "instructions": "call|0x4019a0|    "
            },
            {
                "block_addr": 4225782,
                "constraints": [],
                "instructions": "mov|eax|dword|ptr|rax|    |mov|dword|ptr|rbp|+|0x40|eax|    |or|word|ptr|rbp|+|0x72|1|    |mov|rdi|qword|ptr|rbp|+|0x18|    |call|0x401b60|    "
            },
            {
                "block_addr": 4226632,
                "constraints": [
                    "<Bool|__eq__|LShR|ZeroExt|32|ret|0x1f|0|>    ",
                    "<Bool|__eq__|LShR|ZeroExt|32|mem_0|0x1f|0|>    "
                ],
                "instructions": "xor|ecx|ecx|    |mov|edx|eax|    |mov|rsi|rbp|    |mov|rdi|reg|    |call|0x4071d0|    "
            },
            {
                "block_addr": 4226647,
                "constraints": [],
                "instructions": "test|eax|eax|    |jne|target_0|    "
            },
            {
                "block_addr": 4226655,
                "constraints": [
                    "<Bool|__eq__|ret|0x0|>    "
                ],
                "instructions": "jmp|target_0|    "
            },
            {
                "block_addr": 4224546,
                "constraints": [],
                "instructions": "mov|edi|dword|ptr|reg|+|0x48|    |mov|byte|ptr|rsp|+|0x5f|1|    |mov|rcx|qword|ptr|rbp|+|0x48|    |mov|rdx|qword|ptr|rbp|+|0x38|    |mov|qword|ptr|rsp|+|0x40|0|    |cmp|byte|ptr|rdx|+|rcx|-|1|0x2f|    |lea|rax|rcx|-|1|    |cmovne|rax|rcx|    |and|edi|4|    |mov|qword|ptr|rsp|+|0x48|rax|    |je|target_0|    "
            },
            {
                "block_addr": 4225666,
                "constraints": [
                    "<Bool|__ne__|mem_0|0xb|>    "
                ],
                "instructions": "mov|edi|dword|ptr|reg|+|0x48|    |test|edi|0x100|    |jne|target_0|    "
            },
            {
                "block_addr": 4226155,
                "constraints": [],
                "instructions": "cmp|byte|ptr|rsp|+|0x5d|0|    |jne|target_0|    "
            },
            {
                "block_addr": 4226064,
                "constraints": [
                    "<Bool|__eq__|ret|0|>    ",
                    "<Bool|__eq__|ret|0x0|>    "
                ],
                "instructions": "mov|rdi|reg|    |mov|rbp|qword|ptr|rsp|+|0x20|    |mov|ebx|dword|ptr|reg|    |call|0x401da0|    "
            },
            {
                "block_addr": 4225021,
                "constraints": [
                    "<Bool|__ne__|ret|0x0|>    "
                ],
                "instructions": "cmp|qword|ptr|rsp|+|0x28|reg|    |ja|target_0|    "
            },
            {
                "block_addr": 4225968,
                "constraints": [
                    "<Bool|__ne__|__and__|mem_0|0x100|0x0|>    "
                ],
                "instructions": "lea|rbx|reg|+|0x58|    |mov|rdx|rbp|    |mov|rsi|rbx|    |call|0x407500|    "
            },
            {
                "block_addr": 4225983,
                "constraints": [],
                "instructions": "xor|edx|edx|    |mov|rsi|rbp|    |mov|rdi|reg|    |call|0x406a40|    "
            },
            {
                "block_addr": 4225996,
                "constraints": [],
                "instructions": "mov|edi|dword|ptr|reg|+|0x48|    |mov|rdx|rbp|    |mov|rsi|rbx|    |call|0x407450|    "
            },
            {
                "block_addr": 4226011,
                "constraints": [],
                "instructions": "test|al|al|    |jne|target_0|    "
            },
            {
                "block_addr": 4224906,
                "constraints": [],
                "instructions": "mov|qword|ptr|rsp|+|8|reg|    |mov|rax|qword|ptr|rsp|+|0x20|    |mov|reg|qword|ptr|rax|+|0x18|    |test|reg|reg|    |je|target_0|    "
            },
            {
                "block_addr": 4224595,
                "constraints": [
                    "<Bool|__eq__|__add__|mem_15|mem_14|0xffffffffffffffff|0xffffffffffffffff|>    |<Bool|__ne__|__and__|mem_0|4|0|>    ",
                    "<Bool|__eq__|__add__|mem_15|mem_14|0xffffffffffffffff|0xfffffffffffffffe|>    |<Bool|__ne__|__and__|mem_0|4|0|>    ",
                    "<Bool|__eq__|__add__|mem_76|mem_75|0xffffffffffffffff|0xffffffffffffffff|>    |<Bool|__ne__|__and__|mem_0|4|0|>    ",
                    "<Bool|__eq__|__add__|mem_97|mem_96|0xffffffffffffffff|0xffffffffffffffff|>    |<Bool|__ne__|__and__|mem_0|4|0|>    ",
                    "<Bool|__eq__|__add__|mem_50|mem_49|0xffffffffffffffff|0xffffffffffffffff|>    |<Bool|__ne__|__and__|mem_0|4|0|>    ",
                    "<Bool|__eq__|__add__|mem_70|mem_69|0xffffffffffffffff|0xffffffffffffffff|>    |<Bool|__ne__|__and__|mem_0|4|0|>    "
                ],
                "instructions": "add|rax|qword|ptr|reg|+|0x20|    |lea|rbx|rax|+|1|    |mov|byte|ptr|rax|0x2f|    |mov|qword|ptr|rsp|+|0x40|rbx|    |mov|rax|qword|ptr|rsp|+|0x48|    |mov|rbx|qword|ptr|reg|+|0x30|    |mov|byte|ptr|rsp|+|0x5e|0|    |mov|byte|ptr|rsp|+|0x5d|0|    |mov|qword|ptr|rsp|+|8|0|    |mov|qword|ptr|rsp|+|0x10|0|    |add|rax|1|    |mov|qword|ptr|rsp|+|0x20|rbp|    |sub|rbx|rax|    |mov|qword|ptr|rsp|+|0x18|rax|    |mov|rax|qword|ptr|rbp|+|0x58|    |mov|qword|ptr|rsp|+|0x28|rbx|    |xor|ebx|ebx|    |add|rax|1|    |mov|qword|ptr|rsp|+|0x30|rax|    |jmp|target_0|    "
            },
            {
                "block_addr": 4226152,
                "constraints": [],
                "instructions": "mov|rbp|rax|    |cmp|byte|ptr|rsp|+|0x5d|0|    |jne|target_0|    "
            },
            {
                "block_addr": 4226166,
                "constraints": [],
                "instructions": "test|byte|ptr|reg|+|0x48|4|    |je|target_0|    "
            },
            {
                "block_addr": 4226081,
                "constraints": [],
                "instructions": "mov|rdi|qword|ptr|rsp|+|0x10|    |call|0x406db0|    "
            },
            {
                "block_addr": 4225032,
                "constraints": [
                    "<Bool|__le__|__add__|0xffffffffffffffff|mem_9|__mul__|0xffffffffffffffff|If|__eq__|mem_11|47|__add__|0xffffffffffffffff|mem_0|mem_0|ret|>    ",
                    "<Bool|__le__|__add__|0xffffffffffffffff|mem_9|__mul__|0xffffffffffffffff|If|__eq__|mem_2|47|__add__|0xffffffffffffffff|mem_0|mem_0|ret|>    ",
                    "<Bool|__le__|__add__|0xffffffffffffffff|mem_0|__mul__|0xffffffffffffffff|If|__eq__|mem_28|47|__add__|0xffffffffffffffff|mem_26|mem_26|ret|>    "
                ],
                "instructions": "mov|rax|qword|ptr|reg|+|0x20|    |lea|rsi|reg|+|0x30|    |lea|rdi|reg|+|0x20|    |mov|qword|ptr|rsp|+|0x28|rax|    |mov|rax|qword|ptr|rsp|+|0x48|    |lea|rdx|rax|+|reg|+|2|    |call|0x4070b0|    "
            },
            {
                "block_addr": 4224696,
                "constraints": [
                    "<Bool|__gt__|__add__|0xffffffffffffffff|mem_9|__mul__|0xffffffffffffffff|If|__eq__|mem_11|47|__add__|0xffffffffffffffff|mem_0|mem_0|ret|>    ",
                    "<Bool|__gt__|__add__|0xffffffffffffffff|mem_9|__mul__|0xffffffffffffffff|If|__eq__|mem_2|47|__add__|0xffffffffffffffff|mem_0|mem_0|ret|>    ",
                    "<Bool|__gt__|__add__|0xffffffffffffffff|mem_0|__mul__|0xffffffffffffffff|If|__eq__|mem_28|47|__add__|0xffffffffffffffff|mem_26|mem_26|ret|>    "
                ],
                "instructions": "mov|reg|reg|    |add|reg|qword|ptr|rsp|+|0x18|    |jb|target_0|    "
            },
            {
                "block_addr": 4225829,
                "constraints": [],
                "instructions": "mov|edi|eax|    |call|0x401b50|    "
            },
            {
                "block_addr": 4225594,
                "constraints": [
                    "<Bool|__ne__|__and__|mem_0|16|0|>    "
                ],
                "instructions": "test|al|1|    |mov|edx|0x20000|    |jne|target_0|    "
            },
            {
                "block_addr": 4226660,
                "constraints": [
                    "<Bool|__eq__|__and__|mem_0|56|24|>    "
                ],
                "instructions": "cmp|qword|ptr|rbp|+|0x88|2|    |jne|target_0|    "
            },
            {
                "block_addr": 4226674,
                "constraints": [
                    "<Bool|__eq__|mem_0|0x2|>    "
                ],
                "instructions": "mov|esi|eax|    |mov|rdi|rbp|    |call|0x406f70|    "
            },
            {
                "block_addr": 4226684,
                "constraints": [],
                "instructions": "test|eax|eax|    |jne|target_0|    "
            },
            {
                "block_addr": 4226688,
                "constraints": [
                    "<Bool|__eq__|ret|0x0|>    "
                ],
                "instructions": "mov|eax|dword|ptr|rsp|+|0x64|    |jmp|target_0|    "
            },
            {
                "block_addr": 4226814,
                "constraints": [
                    "<Bool|__ne__|ret|0x0|>    "
                ],
                "instructions": "cmp|dword|ptr|rsp|+|0x58|3|    |jne|target_0|    "
            },
            {
                "block_addr": 4226825,
                "constraints": [
                    "<Bool|__eq__|reg|0x3|>    "
                ],
                "instructions": "mov|eax|dword|ptr|rsp|+|0x64|    |xor|regd|regd|    |mov|ebx|1|    |jmp|target_0|    "
            },
            {
                "block_addr": 4225864,
                "constraints": [
                    "<Bool|__ne__|__and__|mem_0|1|0|>    "
                ],
                "instructions": "xor|edx|edx|    |cmp|qword|ptr|rbp|+|0x58|0|    |setne|dl|    |shl|edx|0x11|    |jmp|target_0|    "
            },
            {
                "block_addr": 4224506,
                "constraints": [
                    "<Bool|__eq__|reg|0xfffffffffe000000|>    |<Bool|__eq__|__add__|mem_0|0x18|0x1a|>    |<Bool|__ne__|mem_2|0x0|>    "
                ],
                "instructions": "mov|rdi|rax|    |call|0x401bc0|    "
            },
            {
                "block_addr": 4224514,
                "constraints": [],
                "instructions": "test|eax|eax|    |mov|dword|ptr|rsp|+|0x64|eax|    |js|target_0|    "
            },
            {
                "block_addr": 4224526,
                "constraints": [
                    "<Bool|__eq__|LShR|ZeroExt|32|ret|0x1f|0|>    "
                ],
                "instructions": "cmp|qword|ptr|reg|+|0x40|0|    |je|target_0|    "
            },
            {
                "block_addr": 4226536,
                "constraints": [
                    "<Bool|__eq__|mem_0|0x0|>    "
                ],
                "instructions": "mov|qword|ptr|rsp|+|0x38|0x186a0|    |mov|byte|ptr|rsp|+|0x5f|1|    |mov|edi|dword|ptr|reg|+|0x48|    |jmp|target_0|    "
            },
            {
                "block_addr": 4226203,
                "constraints": [],
                "instructions": "cmp|qword|ptr|rsp|+|0x50|0|    |jne|target_0|    "
            },
            {
                "block_addr": 4226320,
                "constraints": [],
                "instructions": "test|rbx|rbx|    |jne|target_0|    "
            },
            {
                "block_addr": 4226325,
                "constraints": [],
                "instructions": "cmp|dword|ptr|rsp|+|0x58|3|    |je|target_0|    "
            },
            {
                "block_addr": 4226776,
                "constraints": [
                    "<Bool|__eq__|reg|0x3|>    "
                ],
                "instructions": "movzx|eax|word|ptr|rbp|+|0x70|    |cmp|ax|7|    |je|target_0|    "
            },
            {
                "block_addr": 4226336,
                "constraints": [
                    "<Bool|__ne__|reg|0x3|>    "
                ],
                "instructions": "mov|rdi|qword|ptr|rsp|+|0x10|    |call|0x406db0|    "
            },
            {
                "block_addr": 4226091,
                "constraints": [],
                "instructions": "mov|rdi|qword|ptr|rbp|+|0x18|    |call|0x401b60|    "
            },
            {
                "block_addr": 4225064,
                "constraints": [],
                "instructions": "test|al|al|    |je|target_0|    "
            },
            {
                "block_addr": 4226848,
                "constraints": [
                    "<Bool|__lt__|__add__|ret|0x1|If|__eq__|mem_11|47|__add__|0xffffffffffffffff|mem_0|mem_0|ret|>    ",
                    "<Bool|__lt__|__add__|ret|0x1|If|__eq__|mem_2|47|__add__|0xffffffffffffffff|mem_0|mem_0|ret|>    "
                ],
                "instructions": "mov|rdi|reg|    |mov|rbp|qword|ptr|rsp|+|0x20|    |call|0x401da0|    "
            },
            {
                "block_addr": 4224710,
                "constraints": [
                    "<Bool|__ge__|__add__|ret|0x1|If|__eq__|mem_11|47|__add__|0xffffffffffffffff|mem_0|mem_0|ret|>    ",
                    "<Bool|__ge__|__add__|ret|0x1|If|__eq__|mem_2|47|__add__|0xffffffffffffffff|mem_0|mem_0|ret|>    "
                ],
                "instructions": "mov|rax|qword|ptr|rsp|+|0x30|    |lea|rsi|reg|+|0x108|    |mov|qword|ptr|reg|+|0x58|rax|    |mov|rax|qword|ptr|reg|    |mov|qword|ptr|reg|+|0x48|reg|    |mov|qword|ptr|reg|+|8|rax|    |mov|rax|qword|ptr|rbp|    |mov|qword|ptr|reg|+|0x80|rax|    |mov|eax|dword|ptr|reg|+|0x48|    |test|al|4|    |jne|target_0|    "
            },
            {
                "block_addr": 4226100,
                "constraints": [],
                "instructions": "mov|regd|7|    |mov|qword|ptr|rbp|+|0x18|0|    |mov|qword|ptr|rsp|+|0x10|0|    |mov|word|ptr|rbp|+|0x70|regw|    |or|dword|ptr|reg|+|0x48|0x2000|    |mov|dword|ptr|reg|ebx|    |jmp|target_0|    "
            },
            {
                "block_addr": 4225925,
                "constraints": [
                    "<Bool|__eq__|ret|0xffffffffffffffff|>    ",
                    "<Bool|__eq__|__add__|mem_0|0x70|0x72|>    "
                ],
                "instructions": "mov|rbx|qword|ptr|rsp|+|0x68|    |xor|rbx|qword|ptr|fs:0x28|    |mov|rax|qword|ptr|rsp|+|0x10|    |jne|target_0|    "
            },
            {
                "block_addr": 4225072,
                "constraints": [
                    "<Bool|__ne__|ret|0|>    "
                ],
                "instructions": "mov|rdx|qword|ptr|reg|+|0x20|    |cmp|rdx|qword|ptr|rsp|+|0x28|    |je|target_0|    "
            },
            {
                "block_addr": 4225568,
                "constraints": [],
                "instructions": "movzx|eax|byte|ptr|rsp|+|0x5d|    |jmp|target_0|    "
            },
            {
                "block_addr": 4226861,
                "constraints": [],
                "instructions": "mov|rdi|qword|ptr|rsp|+|0x10|    |call|0x406db0|    "
            },
            {
                "block_addr": 4226871,
                "constraints": [],
                "instructions": "mov|rdi|qword|ptr|rbp|+|0x18|    |call|0x401b60|    "
            },
            {
                "block_addr": 4224760,
                "constraints": [
                    "<Bool|__eq__|__add__|ret|0x58|0xffffffffffffffff|>    |<Bool|__eq__|__add__|ret|0x48|0xffffffffffffffef|>    |<Bool|__eq__|__add__|ret|0x8|0xffffffffffffffaf|>    |<Bool|__eq__|ret|0xfffffffffffffffe|>    |<Bool|__eq__|__add__|ret|0x80|0x27|>    ",
                    "<Bool|__eq__|__add__|ret|0x58|0xffffffffffffffff|>    |<Bool|__eq__|__add__|ret|0x48|0xffffffffffffffef|>    |<Bool|__eq__|__add__|ret|0x8|0xffffffffffffffaf|>    |<Bool|__eq__|__add__|ret|0x80|0x27|>    ",
                    "<Bool|__eq__|__add__|ret|0x58|0xffffffffffffffff|>    |<Bool|__eq__|__add__|ret|0x48|0xffffffffffffffef|>    |<Bool|__eq__|__add__|ret|0x8|0xffffffffffffffaf|>    |<Bool|__eq__|ret|0xffffffffffffffed|>    |<Bool|__eq__|__add__|ret|0x80|0x27|>    "
                ],
                "instructions": "mov|qword|ptr|reg|+|0x30|rsi|    |cmp|qword|ptr|reg|+|0x40|0|    |je|target_0|    "
            },
            {
                "block_addr": 4224764,
                "constraints": [
                    "<Bool|__eq__|__add__|ret|0x30|0xffffffffffffffd7|>    "
                ],
                "instructions": "cmp|qword|ptr|reg|+|0x40|0|    |je|target_0|    "
            },
            {
                "block_addr": 4225950,
                "constraints": [],
                "instructions": "add|rsp|0x78|    |pop|rbx|    |pop|rbp|    |pop|reg|    |pop|reg|    |pop|reg|    |pop|reg|    |ret|    "
            },
            {
                "block_addr": 4225108,
                "constraints": [],
                "instructions": "mov|rcx|qword|ptr|reg|+|0x30|    |sub|rcx|qword|ptr|rsp|+|0x18|    |mov|byte|ptr|rsp|+|0x5d|al|    |mov|qword|ptr|rsp|+|0x28|rcx|    |jmp|target_0|    "
            },
            {
                "block_addr": 4226880,
                "constraints": [],
                "instructions": "mov|regd|7|    |mov|qword|ptr|rbp|+|0x18|0|    |mov|qword|ptr|rsp|+|0x10|0|    |mov|word|ptr|rbp|+|0x70|regw|    |or|dword|ptr|reg|+|0x48|0x2000|    |mov|dword|ptr|reg|0x24|    |jmp|target_0|    "
            },
            {
                "block_addr": 4224780,
                "constraints": [],
                "instructions": "movzx|edx|byte|ptr|rbp|+|0x12|    |and|eax|0x18|    |mov|esi|edx|    |sub|edx|1|    |cmp|eax|0x18|    |je|target_0|    "
            },
            {
                "block_addr": 4226173,
                "constraints": [],
                "instructions": "mov|rax|qword|ptr|rsp|+|0x18|    |cmp|qword|ptr|reg|+|0x30|rax|    |je|target_0|    "
            },
            {
                "block_addr": 4226189,
                "constraints": [
                    "<Bool|__eq__|mem_9|__add__|0x1|If|__eq__|mem_11|47|__add__|0xffffffffffffffff|mem_0|mem_0|>    ",
                    "<Bool|__eq__|mem_9|__add__|0x1|If|__eq__|mem_2|47|__add__|0xffffffffffffffff|mem_0|mem_0|>    "
                ],
                "instructions": "sub|qword|ptr|rsp|+|0x40|1|    |mov|rax|qword|ptr|rsp|+|0x40|    |mov|byte|ptr|rax|0|    |cmp|qword|ptr|rsp|+|0x50|0|    |jne|target_0|    "
            },
            {
                "block_addr": 4226195,
                "constraints": [],
                "instructions": "mov|rax|qword|ptr|rsp|+|0x40|    |mov|byte|ptr|rax|0|    |cmp|qword|ptr|rsp|+|0x50|0|    |jne|target_0|    "
            },
            {
                "block_addr": 4226184,
                "constraints": [
                    "<Bool|__ne__|mem_9|__add__|0x1|If|__eq__|mem_11|47|__add__|0xffffffffffffffff|mem_0|mem_0|>    ",
                    "<Bool|__ne__|mem_9|__add__|0x1|If|__eq__|mem_2|47|__add__|0xffffffffffffffff|mem_0|mem_0|>    "
                ],
                "instructions": "test|rbx|rbx|    |jne|target_0|    "
            },
            {
                "block_addr": 4225376,
                "constraints": [
                    "<Bool|__eq__|__add__|ret|0x58|0xffffffffffffffff|>    |<Bool|__eq__|__add__|ret|0x48|0xffffffffffffffef|>    |<Bool|__eq__|__add__|ret|0x8|0xffffffffffffffaf|>    |<Bool|__eq__|ret|0xfffffffffffffff0|>    |<Bool|__eq__|__add__|ret|0x80|0x27|>    ",
                    "<Bool|__eq__|__add__|ret|0x58|0xffffffffffffffff|>    |<Bool|__eq__|__add__|ret|0x48|0xffffffffffffffef|>    |<Bool|__eq__|__add__|ret|0x8|0xffffffffffffffaf|>    |<Bool|__eq__|ret|0xfd|>    |<Bool|__eq__|__add__|ret|0x80|0x27|>    ",
                    "<Bool|__eq__|__add__|ret|0x58|0xffffffffffffffff|>    |<Bool|__eq__|__add__|ret|0x48|0xffffffffffffffef|>    |<Bool|__eq__|__add__|ret|0x8|0xffffffffffffffaf|>    |<Bool|__eq__|__add__|ret|0x80|0x27|>    "
                ],
                "instructions": "mov|rax|qword|ptr|reg|+|0x38|    |mov|rdi|qword|ptr|rsp|+|0x40|    |mov|qword|ptr|reg|+|0x30|rax|    |mov|rax|qword|ptr|reg|+|0x60|    |lea|rdx|rax|+|1|    |call|0x401cc0|    "
            },
            {
                "block_addr": 4225402,
                "constraints": [
                    "<Bool|__eq__|__add__|ret|0x30|0xffffffffffffffd7|>    "
                ],
                "instructions": "mov|eax|dword|ptr|reg|+|0x48|    |jmp|target_0|    "
            },
            {
                "block_addr": 4224537,
                "constraints": [
                    "<Bool|__ne__|mem_0|0x0|>    "
                ],
                "instructions": "mov|qword|ptr|rsp|+|0x38|-1|    |mov|edi|dword|ptr|reg|+|0x48|    |mov|byte|ptr|rsp|+|0x5f|1|    |mov|rcx|qword|ptr|rbp|+|0x48|    |mov|rdx|qword|ptr|rbp|+|0x38|    |mov|qword|ptr|rsp|+|0x40|0|    |cmp|byte|ptr|rdx|+|rcx|-|1|0x2f|    |lea|rax|rcx|-|1|    |cmovne|rax|rcx|    |and|edi|4|    |mov|qword|ptr|rsp|+|0x48|rax|    |je|target_0|    "
            },
            {
                "block_addr": 4225888,
                "constraints": [
                    "<Bool|__ne__|LShR|ZeroExt|32|ret|0x1f|0|>    "
                ],
                "instructions": "mov|rdi|qword|ptr|rbp|+|0x18|    |call|0x401b60|    "
            },
            {
                "block_addr": 4225897,
                "constraints": [],
                "instructions": "cmp|dword|ptr|rsp|+|0x58|3|    |mov|qword|ptr|rbp|+|0x18|0|    |je|target_0|    "
            },
            {
                "block_addr": 4225916,
                "constraints": [
                    "<Bool|__eq__|ret|0xfffffffffffff800|>    |<Bool|__eq__|__add__|mem_0|0x40|0x42|>    ",
                    "<Bool|__eq__|ret|0xffffff8000000000|>    |<Bool|__eq__|__add__|mem_0|0x40|0x42|>    ",
                    "<Bool|__eq__|ret|0xfffffe0000000000|>    |<Bool|__eq__|__add__|mem_0|0x40|0x42|>    ",
                    "<Bool|__ne__|reg|0x3|>    ",
                    "<Bool|__eq__|ret|0xffffffffffffffe0|>    |<Bool|__eq__|__add__|mem_0|0x40|0x42|>    ",
                    "<Bool|__eq__|ret|0xffffff0000000000|>    |<Bool|__eq__|__add__|mem_0|0x40|0x42|>    ",
                    "<Bool|__eq__|ret|0xffffffffffff0000|>    |<Bool|__eq__|__add__|mem_0|0x40|0x42|>    ",
                    "<Bool|__eq__|ret|0xffc0000000000000|>    |<Bool|__eq__|__add__|mem_0|0x40|0x42|>    "
                ],
                "instructions": "mov|qword|ptr|rsp|+|0x10|0|    |mov|rbx|qword|ptr|rsp|+|0x68|    |xor|rbx|qword|ptr|fs:0x28|    |mov|rax|qword|ptr|rsp|+|0x10|    |jne|target_0|    "
            },
            {
                "block_addr": 4226448,
                "constraints": [
                    "<Bool|__eq__|ret|0x0|>    "
                ],
                "instructions": "cmp|dword|ptr|rsp|+|0x58|3|    |jne|target_0|    "
            },
            {
                "block_addr": 4226459,
                "constraints": [
                    "<Bool|__eq__|reg|0x3|>    "
                ],
                "instructions": "mov|regd|4|    |mov|word|ptr|rbp|+|0x70|regw|    |call|0x4019a0|    "
            },
            {
                "block_addr": 4226475,
                "constraints": [
                    "<Bool|__eq__|__add__|mem_0|0x70|0x72|>    "
                ],
                "instructions": "mov|eax|dword|ptr|rax|    |mov|dword|ptr|rbp|+|0x40|eax|    |jmp|target_0|    "
            },
            {
                "block_addr": 4226019,
                "constraints": [
                    "<Bool|__eq__|ret|0|>    "
                ],
                "instructions": "call|0x4019a0|    "
            },
            {
                "block_addr": 4226024,
                "constraints": [],
                "instructions": "mov|qword|ptr|rsp|+|0x10|0|    |mov|dword|ptr|rax|0xc|    |jmp|target_0|    "
            }
        ]
    },
    "func_name": "fts_build"
}