{
    "GNN_DATA": {
        "edges": [
            {
                "dst": "loopSeerDum",
                "src": 4322608
            }
        ],
        "nodes": [
            {
                "block_addr": 4322608,
                "constraints": [],
                "instructions": "movzx|eax|byte|ptr|rdi|+|0x1c|    |ret|    "
            },
            {
                "block_addr": "loopSeerDum",
                "constraints": [
                    "<Bool|__eq__|__add__|reg|0x1c|0xfffffffffffffffc|>    "
                ],
                "instructions": "no_instructions"
            }
        ]
    },
    "func_name": "i_ring_empty"
}