{
    "GNN_DATA": {
        "edges": [
            {
                "dst": 4227260,
                "src": 4227248
            },
            {
                "dst": 4227274,
                "src": 4227260
            },
            {
                "dst": 4227281,
                "src": 4227274
            },
            {
                "dst": 4227304,
                "src": 4227274
            },
            {
                "dst": 4227295,
                "src": 4227281
            },
            {
                "dst": 4227285,
                "src": 4227281
            },
            {
                "dst": "loopSeerDum",
                "src": 4227295
            },
            {
                "dst": 4227336,
                "src": 4227304
            },
            {
                "dst": 4227308,
                "src": 4227304
            },
            {
                "dst": "loopSeerDum",
                "src": 4227336
            },
            {
                "dst": 4227295,
                "src": 4227285
            },
            {
                "dst": 4227352,
                "src": 4227285
            },
            {
                "dst": 4227313,
                "src": 4227308
            },
            {
                "dst": "loopSeerDum",
                "src": 4227313
            },
            {
                "dst": 4227357,
                "src": 4227352
            },
            {
                "dst": "loopSeerDum",
                "src": 4227357
            }
        ],
        "nodes": [
            {
                "block_addr": 4227248,
                "constraints": [],
                "instructions": "push|reg|    |push|rbp|    |mov|rbp|rdi|    |push|rbx|    |call|0x401730|    "
            },
            {
                "block_addr": 4227260,
                "constraints": [],
                "instructions": "mov|ebx|dword|ptr|rbp|    |mov|rdi|rbp|    |mov|reg|rax|    |call|0x4097a0|    "
            },
            {
                "block_addr": 4227274,
                "constraints": [
                    "<Bool|__eq__|reg|0xffffffffff000000|>    "
                ],
                "instructions": "and|ebx|0x20|    |test|ebx|ebx|    |jne|target_0|    "
            },
            {
                "block_addr": 4227281,
                "constraints": [
                    "<Bool|__eq__|__and__|mem_0|32|0|>    "
                ],
                "instructions": "test|eax|eax|    |je|target_0|    "
            },
            {
                "block_addr": 4227295,
                "constraints": [
                    "<Bool|__ne__|ret|0x0|>    ",
                    "<Bool|__eq__|ret|0x0|>    "
                ],
                "instructions": "pop|rbx|    |pop|rbp|    |pop|reg|    |ret|    "
            },
            {
                "block_addr": "loopSeerDum",
                "constraints": [
                    "<Bool|__eq__|ret|0xfffffffffff00000|>    ",
                    "<Bool|__eq__|ret|0xffffffffffffffff|>    "
                ],
                "instructions": "no_instructions"
            },
            {
                "block_addr": 4227304,
                "constraints": [
                    "<Bool|__ne__|__and__|mem_0|32|0|>    "
                ],
                "instructions": "test|eax|eax|    |jne|target_0|    "
            },
            {
                "block_addr": 4227336,
                "constraints": [
                    "<Bool|__ne__|ret|0x0|>    "
                ],
                "instructions": "pop|rbx|    |mov|eax|0xffffffff|    |pop|rbp|    |pop|reg|    |ret|    "
            },
            {
                "block_addr": 4227285,
                "constraints": [
                    "<Bool|__ne__|ret|0x0|>    "
                ],
                "instructions": "test|reg|reg|    |mov|eax|0xffffffff|    |je|target_0|    "
            },
            {
                "block_addr": 4227308,
                "constraints": [
                    "<Bool|__eq__|ret|0x0|>    "
                ],
                "instructions": "call|0x401700|    "
            },
            {
                "block_addr": 4227313,
                "constraints": [],
                "instructions": "mov|dword|ptr|rax|0|    |mov|eax|0xffffffff|    |pop|rbx|    |pop|rbp|    |pop|reg|    |ret|    "
            },
            {
                "block_addr": 4227352,
                "constraints": [
                    "<Bool|__eq__|ret|0x0|>    "
                ],
                "instructions": "call|0x401700|    "
            },
            {
                "block_addr": 4227357,
                "constraints": [],
                "instructions": "cmp|dword|ptr|rax|9|    |pop|rbx|    |pop|rbp|    |pop|reg|    |setne|al|    |movzx|eax|al|    |neg|eax|    |ret|    "
            }
        ]
    },
    "func_name": "close_stream"
}